ModelAuto/Datapreprocess.py
ModelAuto/FeatureSelection.py
ModelAuto/ModelSelection.py
ModelAuto/Multicollinearity.py
ModelAuto/__init__.py
ModelAuto-0.6.1.dist-info/LICENSE.txt
ModelAuto-0.6.1.dist-info/METADATA
ModelAuto-0.6.1.dist-info/WHEEL
ModelAuto-0.6.1.dist-info/top_level.txt
ModelAuto-0.6.1.dist-info/RECORD
